torch_ort/__init__.py
torch_ort_poc-0.0.4.dist-info/LICENSE
torch_ort_poc-0.0.4.dist-info/METADATA
torch_ort_poc-0.0.4.dist-info/WHEEL
torch_ort_poc-0.0.4.dist-info/top_level.txt
torch_ort_poc-0.0.4.dist-info/RECORD
