Metadata-Version: 2.1
Name: torch-ort-poc
Version: 0.0.4
Summary: training Pytorch models with onnxruntime
Home-page: https://github.com/pytorch/ort
Author: torch_ort contributors
License: UNKNOWN
Project-URL: Bug Tracker, https://github.com/pytorch/ort/issues
Platform: UNKNOWN
Classifier: Programming Language :: Python :: 3
Classifier: License :: OSI Approved :: MIT License
Classifier: Operating System :: OS Independent
Requires-Python: >=3.6
Requires-Dist: onnxruntime-gpu (>=1.7)
Requires-Dist: torch (>=1.8)
